odoo/addons/sale_contact_type/README.rst
odoo/addons/sale_contact_type/__init__.py
odoo/addons/sale_contact_type/__manifest__.py
odoo/addons/sale_contact_type/i18n/es.po
odoo/addons/sale_contact_type/i18n/it.po
odoo/addons/sale_contact_type/i18n/sale_contact_type.pot
odoo/addons/sale_contact_type/models/__init__.py
odoo/addons/sale_contact_type/models/res_partner.py
odoo/addons/sale_contact_type/readme/CONTRIBUTORS.rst
odoo/addons/sale_contact_type/readme/DESCRIPTION.rst
odoo/addons/sale_contact_type/readme/USAGE.rst
odoo/addons/sale_contact_type/static/description/icon.png
odoo/addons/sale_contact_type/static/description/index.html
odoo/addons/sale_contact_type/tests/__init__.py
odoo/addons/sale_contact_type/tests/test_sale_contact_type.py
odoo/addons/sale_contact_type/views/sale_order.xml
odoo14_addon_sale_contact_type-14.0.1.0.1.dev8.dist-info/METADATA
odoo14_addon_sale_contact_type-14.0.1.0.1.dev8.dist-info/WHEEL
odoo14_addon_sale_contact_type-14.0.1.0.1.dev8.dist-info/top_level.txt
odoo14_addon_sale_contact_type-14.0.1.0.1.dev8.dist-info/RECORD
